    [
        {
            "name": "Fiat Egea",
            "prices": { 
                "1-3": 509.99,
                "4-7": 499.99,
                "8-13": 449.99,
                "14-21": 419.99,
                "22+": 389.99
            },
            "class": "Ekonomik",
            "terms": [
                "20 yaş üstü",
                "2.000 KM/Gün",
                "Ehliyat Yaş Sınırı Yok",
                "Kredi Kartı Şartı Yok"
            ],
            "features": [
                "Benzinli",
                "Otomatik",
                "5 Yetişkin",
                "Yolcu Airbag"
            ]
        },
        {
            "name": "Renault Clio",
            "prices": {
                "1-3": 549.99,
                "4-7": 499.99,
                "8-13": 449.99,
                "14-21": 399.99,
                "22+": 359.99
            },
            "class": "Ekonomik",
            "terms": [
                "20 yaş üstü",
                "2.000 KM/Gün",
                "Ehliyat Yaş Sınırı Yok",
                "Kredi Kartı Şartı Yok"
            ],
            "features": [
                "Benzinli",
                "Manuel",
                "5 Yetişkin",
                "Yolcu Airbag"
            ]
        },
        {
            "name": "Renault Taliant",
            "prices": { 
                "1-3": 529.99,
                "4-7": 509.99,
                "8-13": 469.99,
                "14-21": 419.99,
                "22+": 379.99
            },
            "class": "Ekonomik",
            "terms": [
                "20 yaş üstü",
                "2.000 KM/Gün",
                "Ehliyat Yaş Sınırı Yok",
                "Kredi Kartı Şartı Yok"
            ],
            "features": [
                "Benzinli",
                "Manuel",
                "5 Yetişkin",
                "Yolcu Airbag"
            ]
        },
        {
            "name": "Dacia Sandero",
            "prices": {
                "1-3": 559.99,
                "4-7": 519.99,
                "8-13": 499.99,
                "14-21": 469.99,
                "22+": 439.99
            },
            "class": "Ekonomik",
            "terms": [
                "20 yaş üstü",
                "2.000 KM/Gün",
                "Ehliyat Yaş Sınırı Yok",
                "Kredi Kartı Şartı Yok"
            ],
            "features": [
                "Dizel",
                "Manuel",
                "5 Yetişkin",
                "Yolcu Airbag"
            ]
        },
        {
            "name": "Renault Megane",
            "prices": { 
                "1-3": 534.99,
                "4-7": 449.99,
                "8-13": 419.99,
                "14-21": 389.99,
                "22+": 359.99
            },
            "class": "Konfor",
            "terms": [
                "20 yaş üstü",
                "2.000 KM/Gün",
                "Ehliyat Yaş Sınırı Yok",
                "Kredi Kartı Şartı Yok"
            ],
            "features": [
                "Dizel",
                "Otomatik",
                "5 Yetişkin",
                "Yolcu Airbag"
            ]
        },
        {
            "name": "Ford Focus",
            "prices": { 
                "1-3": 579.99,
                "4-7": 549.99,
                "8-13": 509.99,
                "14-21": 489.99,
                "22+": 469.99
            },
            "class": "Konfor",
            "terms": [
                "20 yaş üstü",
                "2.000 KM/Gün",
                "Ehliyat Yaş Sınırı Yok",
                "Kredi Kartı Şartı Yok"
            ],
            "features": [
                "Benzinli",
                "Otomatik",
                "5 Yetişkin",
                "Yolcu Airbag"
            ]
        },
        {
            "name": "Opel Combo",
            "prices": {
                "1-3": 509.99,
                "4-7": 499.99,
                "8-13": 449.99,
                "14-21": 419.99,
                "22+": 389.99
            },
            "class": "Ekonomik",
            "terms": [
                "20 yaş üstü",
                "2.000 KM/Gün",
                "Ehliyat Yaş Sınırı Yok",
                "Kredi Kartı Şartı Yok"
            ],
            "features": [
                "Benzinli",
                "Otomatik",
                "5 Yetişkin",
                "Yolcu Airbag"
            ]
        },
        {
            "name": "Honda Civic",
            "prices": {
                "1-3": 509.99,
                "4-7": 499.99,
                "8-13": 449.99,
                "14-21": 419.99,
                "22+": 389.99
            },
            "class": "Ekonomik",
            "terms": [
                "20 yaş üstü",
                "2.000 KM/Gün",
                "Ehliyat Yaş Sınırı Yok",
                "Kredi Kartı Şartı Yok"
            ],
            "features": [
                "Benzinli",
                "Otomatik",
                "5 Yetişkin",
                "Yolcu Airbag"
            ]
        },
        {
            "name": "Volkswagen Passat",
            "prices": {
                "1-3": 509.99,
                "4-7": 499.99,
                "8-13": 449.99,
                "14-21": 419.99,
                "22+": 389.99
            },
            "class": "Ekonomik",
            "terms": [
                "20 yaş üstü",
                "2.000 KM/Gün",
                "Ehliyat Yaş Sınırı Yok",
                "Kredi Kartı Şartı Yok"
            ],
            "features": [
                "Benzinli",
                "Otomatik",
                "5 Yetişkin",
                "Yolcu Airbag"
            ]
        },
        {
            "name": "Ford Kuga",
            "prices": {
                "1-3": 509.99,
                "4-7": 499.99,
                "8-13": 449.99,
                "14-21": 419.99,
                "22+": 389.99
            },
            "class": "Ekonomik",
            "terms": [
                "20 yaş üstü",
                "2.000 KM/Gün",
                "Ehliyat Yaş Sınırı Yok",
                "Kredi Kartı Şartı Yok"
            ],
            "features": [
                "Benzinli",
                "Otomatik",
                "5 Yetişkin",
                "Yolcu Airbag"
            ]
        },
        {
            "name": "Jeep Renegade",
            "prices": {
                "1-3": 509.99,
                "4-7": 499.99,
                "8-13": 449.99,
                "14-21": 419.99,
                "22+": 389.99
            },
            "class": "Ekonomik",
            "terms": [
                "20 yaş üstü",
                "2.000 KM/Gün",
                "Ehliyat Yaş Sınırı Yok",
                "Kredi Kartı Şartı Yok"
            ],
            "features": [
                "Benzinli",
                "Otomatik",
                "5 Yetişkin",
                "Yolcu Airbag"
            ]
        }
    ]